setup.py
yabormeparser/__init__.py
yabormeparser/act.py
yabormeparser/loggingopt.py
yabormeparser/parser.py
yabormeparser/parser2.py
yabormeparser.egg-info/PKG-INFO
yabormeparser.egg-info/SOURCES.txt
yabormeparser.egg-info/dependency_links.txt
yabormeparser.egg-info/entry_points.txt
yabormeparser.egg-info/requires.txt
yabormeparser.egg-info/top_level.txt
yabormeparser/annoucement/__init__.py
yabormeparser/annoucement/ampliacion_de_capital.py
yabormeparser/annoucement/ceses_dimisiones.py
yabormeparser/annoucement/common.py
yabormeparser/annoucement/constitucion.py
yabormeparser/annoucement/filters.py
yabormeparser/annoucement/nombramientos.py
yabormeparser/annoucement/parser.py
yabormeparser/annoucement/positiondict.py