Metadata-Version: 1.1
Name: yabormeparser
Version: 0.3
Summary: A parser than transform PDF BORME files into a BORME JSON files.
Home-page: https://github.com/funeslab/yabormeparser/
Author: Daniel A. Dorado
Author-email: daniel@funeslab.com
License: GPLv3+
Keywords: BORME,transparency,opendata,Spain,Registro mercantil,Boletín Oficial del Registro Mercantil
Platform: UNKNOWN
Classifier: Development Status :: 3 - Alpha
Classifier: Environment :: Console
Classifier: Intended Audience :: Developers
Classifier: License :: OSI Approved :: GNU General Public License v3 or later (GPLv3+)
Classifier: Natural Language :: Spanish
Classifier: Operating System :: OS Independent
Classifier: Programming Language :: Python
Classifier: Topic :: Text Processing
